simple_loggers/__init__.py
simple_loggers/version/version.json
simple_loggers-1.0.5.dist-info/METADATA
simple_loggers-1.0.5.dist-info/WHEEL
simple_loggers-1.0.5.dist-info/top_level.txt
simple_loggers-1.0.5.dist-info/RECORD
