Metadata-Version: 2.1
Name: simple-loggers
Version: 1.0.5
Summary: A Simple Logger Package
Home-page: https://github.com/suqingdong/simple-loggers
Author: suqingdong
Author-email: 1078595229@qq.com
License: BSD License
Project-URL: Tracker, https://github.com/suqingdong/simple-loggers/issues
Platform: UNKNOWN
Classifier: Development Status :: 5 - Production/Stable
Classifier: Operating System :: OS Independent
Classifier: Intended Audience :: Developers
Classifier: License :: OSI Approved :: MIT License
Classifier: Programming Language :: Python
Classifier: Programming Language :: Python :: 2
Classifier: Programming Language :: Python :: 2.7
Classifier: Programming Language :: Python :: 3
Classifier: Programming Language :: Python :: 3.6
Classifier: Topic :: Software Development :: Libraries
